flomo2md/__init__.py
flomo2md/__main__.py
flomo2md-0.1.0.dist-info/METADATA
flomo2md-0.1.0.dist-info/WHEEL
flomo2md-0.1.0.dist-info/entry_points.txt
flomo2md-0.1.0.dist-info/RECORD
