Metadata-Version: 2.1
Name: Flomo2MD
Version: 0.1.0
Summary: convert flomo's HTML to markdown.
Home-page: https://github.com/largomst/flomo2md
Author: largomst
Author-email: dingrui.zhen@gmail.com
Requires-Python: >=3.10,<4.0
Classifier: Development Status :: 3 - Alpha
Classifier: License :: OSI Approved :: MIT License
Classifier: Operating System :: MacOS
Classifier: Programming Language :: Python :: 3
Classifier: Programming Language :: Python :: 3.10
Classifier: Programming Language :: Python :: 3.11
Classifier: Programming Language :: Python :: 3.12
Requires-Dist: markdownify (>=0.13.1,<0.14.0)
Requires-Dist: rich (>=13.9.3,<14.0.0)
Project-URL: Repository, https://github.com/largomst/flomo2md
